Workbook
Name Slicer_Category: #N/A
Name Slicer_City: #N/A
Name Slicer_Gender: #N/A
Name Slicer_Months__Order_Date: #N/A
Name Slicer_Sub_Category: #N/A
Name Slicer_Years__Order_Date: #N/A

Sheet Charts or Graphs
B2: Column or Bar Chart
A4: 1 | B4: Column chart | C4: When we use column or bar chart
B5: Vertical bars | C5: e.g . 1. regon wise total sales
A6: 2 | B6: Bar charts | C6: 2. year wise total profit
B7: Horizontal bars | C7: 3. category wise total qty ordered
B9: Column chart ( Vertical ) | C9: Text | D9: Numeric
C10: X-axis | D10: Y -axis
B11: Bar chart ( Horizantal) | C11: Text | D11: Numeric
C12: Y-axis | D12: X -axis
B14: Pie or Donought Chart
H16: Year | I16: Sum of Sales
A17: 3 | B17: Pie chart | C17: When we want to display % contribution | H17: 2021 | I17: 98294.64
H18: 2022 | I18: 133235.85
A19: 4 | B19: Donought chart | C19: When we want to display % contribution | H19: 2023 | I19: 135261.51
C20: e.g. calculate year wise % of total sales | H20: 2024 | I20: 222858.11
H21: Grand Total | I21: 589650.1
I23: =GETPIVOTDATA("Sales",$H$16,"Year","2024")/GETPIVOTDATA("Sales",$H$16) -> 0.37794974
A29: 5 | B29: DASHBOARD | C29: it is a visual display of important information ,shown in a single screen or page using charts,numbers,tables,slicers(filter) KPI'S
C30: it is used to monitor performance,tracktrends and make decisions
C31: e.g. Bike (meter)==> performance display
A34: 6 | B34: Tree map/Hierarchy chart | C34: Top 5 ====> data outside copy and paste
A36: 7 | B36: Funnel Chart | C36: Top / Bottom display ====> data outside copy and paste
A39: 8 | B39: Line or Axis Chart | C39: Time seies data
C40: to show trends
A42: 9 | B42: Map Chart | C42: Location / City / Region ====> data outside copy and paste
A45: 10 | B45: Scatter Chart | C45: To show relation between two numeric columns
C46: e.g. Sales vs Profit ==> numeric to numeric data
B49: e.g | C49: Car age | D49: Car Price
C50: 1 | D50: 5000
C51: 2 | D51: 4000
C52: 3 | D52: 3500
C53: 4 | D53: 3000
C54: 5 | D54: 2500
C55: 6 | D55: 2000
C56: 7 | D56: 1000
C57: 8 | D57: 900
D66: Height | E66: Weight
D67: 130 | E67: 30
D68: 140 | E68: 40
D69: 145 | E69: 50
D70: 150 | E70: 60
D71: 155 | E71: 70
D72: 160 | E72: 80
A91: 11 | B91: Histogram | C91: Single column numeric ======> pivot table not cteate
C92: To show frequency distribution
A96: 12 | B96: Boxplot | C96: Single column numeric
C97: To show outliers from the data
C98: Outliers : The points that are not matching with rest of the data points
C99: very small or very large
C102: Age
C103: 45
C104: 23
C105: 52
C106: 56
C107: 78
C108: 52
C109: 23
C110: 20
C111: 200
C112: -700
C113: -900
C114: 900
A141: 13 | B141: Combo chart | C141: Line chart with bar chart
C142: create pivot table : monthwise total sales and profit
C143: (only two values)
C146: Row Labels | D146: Sum of Sales | E146: Sum of Profit
C147: Jan | D147: 40776.15 | E147: 9249.93
C148: Feb | D148: 34869.72 | E148: 7253.34
C149: Mar | D149: 25832.685 | E149: 4520.175
C150: Apr | D150: 38287.785 | E150: 8416.725
C151: May | D151: 47050.38 | E151: 11815.14
C152: Jun | D152: 75494.22 | E152: 19511.55
C153: Jul | D153: 39468.285 | E153: 6951.255
C154: Aug | D154: 50235.45 | E154: 11513.07
C155: Sep | D155: 70709.64 | E155: 13654.05
C156: Oct | D156: 62997.375 | E156: 11722.455
C157: Nov | D157: 49089.765 | E157: 11187.375
C158: Dec | D158: 54838.65 | E158: 13276.77
C159: Grand Total | D159: 589650.1 | E159: 129071.84
A165: 14 | B165: Cluster bar chart | C165: When we have one text column and two numeric column
C166: Mltiple columns bar : side by side
C169: Row Labels | D169: Sum of Sales | E169: Sum of Profit | F169: Sum of Quantity
C170: Jan | D170: 40776.15 | E170: 9249.93 | F170: 460
C171: Feb | D171: 34869.72 | E171: 7253.34 | F171: 317
C172: Mar | D172: 25832.685 | E172: 4520.175 | F172: 304
C173: Apr | D173: 38287.785 | E173: 8416.725 | F173: 329
C174: May | D174: 47050.38 | E174: 11815.14 | F174: 455
C175: Jun | D175: 75494.22 | E175: 19511.55 | F175: 615
C176: Jul | D176: 39468.285 | E176: 6951.255 | F176: 389
C177: Aug | D177: 50235.45 | E177: 11513.07 | F177: 570
C178: Sep | D178: 70709.64 | E178: 13654.05 | F178: 599
C179: Oct | D179: 62997.375 | E179: 11722.455 | F179: 579
C180: Nov | D180: 49089.765 | E180: 11187.375 | F180: 550
C181: Dec | D181: 54838.65 | E181: 13276.77 | F181: 591
C182: Grand Total | D182: 589650.1 | E182: 129071.84 | F182: 5758
A190: 15 | B190: Stacked bar chart | C190: When we have one text column and two numeric column
C191: Multiple column bar : Layer by layer
C194: Row Labels | D194: Sum of Sales | E194: Sum of Profit | F194: Sum of Quantity
C195: Jan | D195: 40776.15 | E195: 9249.93 | F195: 460
C196: Feb | D196: 34869.72 | E196: 7253.34 | F196: 317
...

Sheet Sheet1

Sheet KPI
A2: KPI | B2: Key Performance Indecator is a measurable value that shows how well a business,team or process is achieving its goals
B3: it tells you whether performance is improving,declining or staying the same
B4: e.g Toal Sales
B5: Total customers
B6: Total orders
B7: Revenue growth %
B8: Total profit

Sheet DASHBOARD1

Sheet DASHBOARD2

Sheet DASHBOARD3

Sheet Dataset
A1: Row ID | B1: Order ID | C1: Ship Mode | D1: Customer ID | E1: Customer Name | F1: Segment | G1: City | H1: State | I1: Country | J1: Region | K1: Product ID | L1: Category | M1: Sub-Category | N1: Product Name | O1: Sales | P1: Quantity | Q1: Profit | R1: Shipping Cost | S1: Order Priority | T1: Target | U1: Manager | V1: Team lead | W1: Gender | X1: Order Date | Y1: Month | Z1: Year | AA1: Ship Date
A2: 1 | B2: IN-2014-54694 | C2: Standard Class | D2: HG-14845 | E2: Harry Greene | F2: Consumer | G2: Rajkot | H2: Gujarat | I2: India | J2: West | K2: OFF-BI-10001312 | L2: Office Supplies | M2: Binders | N2: Cardinal 3-Hole Punch, Clear | O2: 56.52 | P2: 2 | Q2: 23.7 | R2: 2.15 | S2: Medium | T2: 386 | U2: Mahesh | V2: Mohit | W2: Male | X2: 45303 | Y2: =TEXT(X2,"MMMM") -> January | Z2: =TEXT(X2,"YYYY") -> 2024 | AA2: 45424
A3: 2 | B3: IN-2013-53763 | C3: Standard Class | D3: AR-10510 | E3: Andrew Roberts | F3: Consumer | G3: Durg | H3: Chhattisgarh | I3: India | J3: East | K3: OFF-BI-10002386 | L3: Office Supplies | M3: Binders | N3: Acco Index Tab, Clear | O3: 17.16 | P3: 2 | Q3: 2.04 | R3: 1.5 | S3: Medium | T3: 401 | U3: Mahesh | V3: Mohan | W3: Female | X3: 45287 | Y3: =TEXT(X3,"MMMM") -> December | Z3: =TEXT(X3,"YYYY") -> 2023 | AA3: 45291
A4: 3 | B4: IN-2014-15473 | C4: Standard Class | D4: TP-21130 | E4: Theone Pippenger | F4: Consumer | G4: Mangalore | H4: Karnataka | I4: India | J4: South | K4: OFF-BI-10004436 | L4: Office Supplies | M4: Binders | N4: Acco Hole Reinforcements, Recycled | O4: 14.04 | P4: 2 | Q4: 0.24 | R4: 0.79 | S4: Medium | T4: 293 | U4: Mahesh | V4: Manu | W4: Female | X4: 45334 | Y4: =TEXT(X4,"MMMM") -> February | Z4: =TEXT(X4,"YYYY") -> 2024 | AA4: 45485
A5: 4 | B5: IN-2014-24622 | C5: Standard Class | D5: MM-17920 | E5: Michael Moore | F5: Consumer | G5: Bijapur | H5: Karnataka | I5: India | J5: South | K5: OFF-BI-10002885 | L5: Office Supplies | M5: Binders | N5: Avery Hole Reinforcements, Recycled | O5: 9.54 | P5: 2 | Q5: 4.44 | R5: 0.14 | S5: Medium | T5: 609 | U5: Mahesh | V5: Meena | W5: Female | X5: 45587 | Y5: =TEXT(X5,"MMMM") -> October | Z5: =TEXT(X5,"YYYY") -> 2024 | AA5: 45593
A6: 5 | B6: IN-2012-29130 | C6: Standard Class | D6: JR-15700 | E6: Jocasta Rupert | F6: Consumer | G6: Kollam | H6: Kerala | I6: India | J6: South | K6: OFF-ST-10001290 | L6: Office Supplies | M6: Storage | N6: Rogers Shelving, Single Width | O6: 124.32 | P6: 2 | Q6: 54.66 | R6: 11.12 | S6: Medium | T6: 750 | U6: Mahesh | V6: Mohan | W6: Male | X6: 44466 | Y6: =TEXT(X6,"MMMM") -> September | Z6: =TEXT(X6,"YYYY") -> 2021 | AA6: 44206
A7: 6 | B7: IN-2013-22648 | C7: Standard Class | D7: SF-20065 | E7: Sandra Flanagan | F7: Consumer | G7: Ratlam | H7: Madhya Pradesh | I7: India | J7: West | K7: OFF-ST-10000327 | L7: Office Supplies | M7: Storage | N7: Smead Folders, Wire Frame | O7: 33.12 | P7: 2 | Q7: 4.62 | R7: 0.91 | S7: Medium | T7: 647 | U7: Mahesh | V7: Manu | W7: Female | X7: 44728 | Y7: =TEXT(X7,"MMMM") -> June | Z7: =TEXT(X7,"YYYY") -> 2022 | AA7: 44734
A8: 7 | B8: IN-2011-24769 | C8: Standard Class | D8: JM-15535 | E8: Jessica Myrick | F8: Consumer | G8: Solapur | H8: Maharashtra | I8: India | J8: West | K8: OFF-EN-10003632 | L8: Office Supplies | M8: Envelopes | N8: Jiffy Mailers, Recycled | O8: 71.94 | P8: 2 | Q8: 10.74 | R8: 8.46 | S8: Medium | T8: 167 | U8: Mahesh | V8: Meena | W8: Female | X8: 45060 | Y8: =TEXT(X8,"MMMM") -> May | Z8: =TEXT(X8,"YYYY") -> 2023 | AA8: 45066
A9: 8 | B9: IN-2012-43165 | C9: Standard Class | D9: MM-17260 | E9: Magdelene Morse | F9: Consumer | G9: Puducherry | H9: Puducherry | I9: India | J9: South | K9: OFF-EN-10002007 | L9: Office Supplies | M9: Envelopes | N9: Kraft Clasp Envelope, with clear poly window | O9: 25.08 | P9: 2 | Q9: 3.96 | R9: 1.88 | S9: Medium | T9: 189 | U9: Mahesh | V9: Mohit | W9: Female | X9: 44325 | Y9: =TEXT(X9,"MMMM") -> May | Z9: =TEXT(X9,"YYYY") -> 2021 | AA9: 44509
A10: 9 | B10: IN-2012-32882 | C10: Standard Class | D10: TR-21325 | E10: Toby Ritter | F10: Consumer | G10: Kanpur | H10: Uttar Pradesh | I10: India | J10: North | K10: OFF-LA-10003273 | L10: Office Supplies | M10: Labels | N10: Harbour Creations Color Coded Labels, Adjustable | O10: 21.6 | P10: 2 | Q10: 1.26 | R10: 1.38 | S10: Medium | T10: 774 | U10: Mahesh | V10: Mohan | W10: Male | X10: 44585 | Y10: =TEXT(X10,"MMMM") -> January | Z10: =TEXT(X10,"YYYY") -> 2022 | AA10: 44591
A11: 10 | B11: IN-2011-59510 | C11: Standard Class | D11: DK-12985 | E11: Darren Koutras | F11: Consumer | G11: Meerut | H11: Uttar Pradesh | I11: India | J11: North | K11: OFF-LA-10002272 | L11: Office Supplies | M11: Labels | N11: Smead File Folder Labels, Alphabetical | O11: 17.4 | P11: 2 | Q11: 1.38 | R11: 1.36 | S11: Medium | T11: 389 | U11: Mahesh | V11: Manu | W11: Female | X11: 44790 | Y11: =TEXT(X11,"MMMM") -> August | Z11: =TEXT(X11,"YYYY") -> 2022 | AA11: 44795
A12: 11 | B12: IN-2014-63766 | C12: Standard Class | D12: MK-18160 | E12: Mike Kennedy | F12: Consumer | G12: Mangalore | H12: Karnataka | I12: India | J12: South | K12: OFF-LA-10004745 | L12: Office Supplies | M12: Labels | N12: Harbour Creations Shipping Labels, Adjustable | O12: 18.72 | P12: 2 | Q12: 9.12 | R12: 1.26 | S12: Medium | T12: 585 | U12: Mahesh | V12: Meena | W12: Male | X12: 44273 | Y12: =TEXT(X12,"MMMM") -> March | Z12: =TEXT(X12,"YYYY") -> 2021 | AA12: 44278
A13: 12 | B13: IN-2011-78823 | C13: Standard Class | D13: ME-17725 | E13: Max Engle | F13: Consumer | G13: Raipur | H13: Rajasthan | I13: India | J13: West | K13: OFF-FA-10000577 | L13: Office Supplies | M13: Fasteners | N13: Stockwell Push Pins, 12 Pack | O13: 26.82 | P13: 2 | Q13: 13.38 | R13: 2.49 | S13: Medium | T13: 146 | U13: Mahesh | V13: Mohit | W13: Male | X13: 45618 | Y13: =TEXT(X13,"MMMM") -> November | Z13: =TEXT(X13,"YYYY") -> 2024 | AA13: 45622
... A1556: 1555 | B1556: IN-2013-14675 | C1556: Standard Class | D1556: CS-12130 | E1556: Chad Sievert | F1556: Consumer | G1556: Bilaspur | H1556: Uttar Pradesh | I1556: India | J1556: North | K1556: TEC-CO-10002035 | L1556: Technology | M1556: Copiers | N1556: Canon Wireless Fax, High-Speed | O1556: 753.72 | P1556: 2 | Q1556: 60.24 | R1556: 74.65 | S1556: Medium | T1556: 542 | U1556: Suresh | V1556: Sunil | W1556: Female | X1556: 44587 | Y1556: =TEXT(X1556,"MMMM") -> January | Z1556: =TEXT(X1556,"YYYY") -> 2022 | AA1556: 44591

Sheet Questions
A1: Sales, Profit, and Quantity Analysis | J1: Q1 | K1: KPI'S
J2: Total Sales | K2: Total Profit | L2: Total Qty orders | N2: Total Orders | O2: Total Customers | AD2: unique key or pivot table used ==> Total count value-- 494
A3: 1. What is the total Sales, Profit, and Quantity sold across all records? | J3: =SUM(Dataset!O2:O1556) -> 589650.1 | K3: =SUM(Dataset!Q2:Q1556) -> 129071.84 | L3: =SUM(Dataset!P2:P1556) -> 5758 | N3: =COUNTA(Dataset!B2:B1556) -> 1555 | O3: =COUNTA(_xlfn.UNIQUE(Dataset!E2:E1556)) -> 494
AE4: Row Labels
A5: 2. Which Product Name has the highest Sales? | AE5: Aaron Bergman
J6: Total Sales | K6: Total Profit | L6: Total Quantity | AE6: Aaron Hawkins
A7: 3. Which Customer placed the highest number of orders? | J7: 589650.1 | K7: 129071.84 | L7: 5758 | AE7: Adam Hart
AE8: Adam Shillingsburg
A9: 4. What is the average Sales and Profit per order? | AE9: Adrian Barton
AE10: Adrian Shami
A11: 5. Which Region has the highest total profit? | AE11: Alan Barnes
AE12: Alan Dominguez
AE13: Alan Haines
AE14: Alan Schoenberger
A15: 2. Date & Time Based Questions | AE15: Alan Shonely
AE16: Alejandro Ballentine
A17: 6. How many orders were placed in each year? | AE17: Alejandro Grove
AE18: Alejandro Savely
A19: 7. Calculate the number of days taken to ship each order (Ship Date - Order Date). What is the average shipping time? | AE19: Alex Avila
AE20: Alex Russell
A21: 8. Identify orders where shipping took more than 10 days. | AE21: Alice McCarthy
AE22: Allen Armold
A23: 9. Count how many orders were placed in each month. | AE23: Allen Rosenblatt
AE24: Alyssa Tate
A25: 10. Which month had the highest Sales? | AE25: Amy Cox
AE26: Amy Hunt
AE27: Andrew Gjertsen
AE28: Andrew Roberts
A29: 3. Location-Based Questions | AE29: Andy Gerbode
AE30: Andy Reiter
A31: 11. What are the total Sales and Profit by State? | AE31: Andy Yotov
AE32: Anemone Ratner
A33: 12. Which City contributed the most to overall profit? | AE33: Ann Blume
AE34: Ann Chong
A35: 13. Group Sales by Region and compare average Shipping Cost per region. | AE35: Ann Steele
AE36: Anna Andreadi
A37: 14. Which states have negative profit? | AE37: Anna HŠberlin
AE38: Anne Pryor
AE39: Anthony Garverick
AE40: Anthony Jacobs
A41: 4. Product/Category Questions | AE41: Anthony Johnson
AE42: Anthony O'Donnell
A43: 15. What is the total sales for each Sub-Category? | AE43: Anthony Rawles
AE44: Anthony Witt
A45: 16. Find out the most profitable and least profitable Sub-Category. | AE45: Art Ferguson
AE46: Art Foster
A47: 17. Which Category has the highest Shipping Cost? | AE47: Arthur Gainer
AE48: Arthur Prichep
A49: 18. List all unique Product Names sold in Karnataka. | AE49: Arthur Wiediger
AE50: Ashley Jarboe
AE51: Astrea Jones
AE52: Barbara Fisher
A53: 5. Manager & Team Questions | AE53: Barry Franz
AE54: Barry Franzšsisch
A55: 19. Which Team Lead has managed the highest sales? | AE55: Barry Gonzalez
AE56: Bart Folk
A57: 20. Group data by Manager and find average profit per order. | AE57: Bart Watters
AE58: Ben Wallace
A59: 21. Which Team Lead has the highest average shipping cost per order? | AE59: Benjamin Farhat
AE60: Benjamin Patterson
AE61: Bill Donatelli
AE62: Bill Eplett
A63: 6. Customer & Gender Based | AE63: Bill Overfelt
AE64: Bill Shonely
A65: 22. Count the number of male vs. female customers. | AE65: Bobby Elias
AE66: Bobby Odegard
A67: 23. What is the total sales by gender? | AE67: Brad Eason
AE68: Brad Norvell
A69: 24. Who are the top 5 customers by total profit earned? | AE69: Brad Thomas
AE70: Bradley Drucker
AE71: Bradley Nguyen
AE72: Bradley Talbott
A73: 7. Filter-Based / Condition-Based | AE73: Brendan Dodson
AE74: Brendan Sweed
A75: 25. How many orders have Sales between ₹200 and ₹500? | AE75: Brian DeCherney
AE76: Brian Derr
A77: 26. List all orders where “Column4” is “Not ok”. | AE77: Brian Stugart
AE78: Brooke Gillingham
A79: 27. Find customers who placed more than 2 orders (you’ll need to group). | AE79: Bruce Degenhardt
AE80: Bruce Geld
A81: 28. Which orders have negative profit? | AE81: Bruce Stewart
AE82: Bryan Davis
AE83: Bryan Mills
AE84: Cari Sayre
A85: 8. Pivot Table / Chart Based | AE85: Carl Weiss
AE86: Carlos Soltero
A87: 29. Create a Pivot Table to show Sub-Category-wise Sales and Profit. | AE87: Carol Triggs
AE88: Caroline Jumper
A89: 30. Create a line chart showing monthly sales trends over the year. | AE89: Cassandra Brandow
AE90: Catherine Glotzbach
AE91: Cathy Armstrong
AE92: Chad Cunningham
A93: A. Sales, Quantity & Profit Analysis | AE93: Chad McGuire
AE94: Chad Sievert
A95: 1. Show total Sales, Quantity, and Profit by Category. | AE95: Charles Crestani
AE96: Charles Sheldon
A97: 2. Create a Pivot Table showing total Sales by Sub-Category and Region. | AE97: Chris McAfee
AE98: Chris Selesnick
A99: 3. Find average Profit per Order by Ship Mode. | AE99: Christina Anderson
AE100: Christina DeMoss
...

Sheet Solutions
A1: 1. Sales, Profit, and Quantity Analysis
A3: 1. What is the total Sales, Profit, and Quantity sold across all records?
A4: Q1. Ans
A6: KPI'S
A7: Total Sales | B7: Total Profit | C7: Total Qty orders | E7: Total Orders | F7: Total Customers
A8: =SUM(Dataset!O2:O1556) -> 589650.1 | B8: =SUM(Dataset!Q2:Q1556) -> 129071.84 | C8: =SUM(Dataset!P2:P1556) -> 5758 | E8: =COUNTA(Dataset!B2:B1556) -> 1555 | F8: =COUNTA(_xlfn.UNIQUE(Dataset!E2:E1556)) -> 494
A11: Total Sales | B11: Total Profit | C11: Total Quantity
A12: 589650.1 | B12: 129071.84 | C12: 5758
A14: Total Sales | B14: Total Profit | C14: Total Quantity
A15: 589650.1 | B15: 129071.84 | C15: 5758
A18: Q2. Ans
A20: Product Name | B20: Sum of Sales
A21: Motorola Smart Phone, with Caller ID | B21: 9683.1
A22: Sauder Classic Bookcase, Traditional | B22: 7847.82
A23: Apple Smart Phone, Full Size | B23: 7650
A24: Cisco Smart Phone, Full Size | B24: 5870.25
A25: Bush Library with Doors, Metal | B25: 5820.48
A26: Grand Total | B26: 36871.65
A36: Q3.Ans
A39: Customer Name | B39: Count of Order ID
A40: Arthur Gainer | B40: 17
A41: Katherine Ducich | B41: 12
A42: Luke Foster | B42: 11
A43: Lena Radford | B43: 10
A44: Lisa DeCherney | B44: 10
A45: Harry Greene | B45: 10
A46: Jessica Myrick | B46: 10
A47: Richard Bierner | B47: 9
A48: Corey-Lock | B48: 9
A49: Stewart Carmichael | B49: 9
A50: Alejandro Savely | B50: 9
A51: Frank Gastineau | B51: 9
A52: Grand Total | B52: 125
A59: Ordered id | B59: Average of Sales | C59: Average of Profit
A60: IN-2012-26274 | B60: 2761.29 | C60: 180.99
A61: IN-2012-29571 | B61: 3187.5 | C61: 350.55
A62: IN-2012-79439 | B62: 3076.5 | C62: 215.25
A63: IN-2013-46798 | B63: 3180.3 | C63: 381.6
A64: IN-2013-50809 | B64: 5751.54 | C64: 2817.99
A65: Grand Total | B65: 3453.07 | C65: 687.895
A75: Q5. Ans
A77: Region | B77: Sum of Sales
A78: East | B78: 96322.02
A79: North | B79: 162199.68
A80: South | B80: 142453.08
A81: West | B81: 188675.32
A82: Grand Total | B82: 589650.1
A90: 2. Date & Time Based Questions
A94: Q9. Ans | F94: we can't create tree map chart and funnel chart direct on pivot table
B97: Row Labels | C97: Count of Order ID | F97: Month | G97: Total Ordered
B98: Jan | C98: 117 | F98: Jan | G98: =C98 -> 117
B99: Feb | C99: 84 | F99: Feb | G99: =C99 -> 84
B100: Mar | C100: 88 | F100: Mar | G100: =C100 -> 88
B101: Apr | C101: 83 | F101: Apr | G101: =C101 -> 83
B102: May | C102: 126 | F102: May | G102: =C102 -> 126
B103: Jun | C103: 159 | F103: Jun | G103: =C103 -> 159
B104: Jul | C104: 113 | F104: Jul | G104: =C104 -> 113
B105: Aug | C105: 149 | F105: Aug | G105: =C105 -> 149
B106: Sep | C106: 152 | F106: Sep | G106: =C106 -> 152
B107: Oct | C107: 153 | F107: Oct | G107: =C107 -> 153
B108: Nov | C108: 163 | F108: Nov | G108: =C108 -> 163
B109: Dec | C109: 168 | F109: Dec | G109: =C109 -> 168
B110: Grand Total | C110: 1555
A118: Top 5 Team Lead in Sales
A120: Row Labels | B120: Sum of Sales | D120: Team Lead | E120: Sum of Sales
A121: Manu | B121: 55627.785 | D121: Manu | E121: =B121 -> 55627.785
A122: Meena | B122: 51572.01 | D122: Meena | E122: =B122 -> 51572.01
A123: Mohit | B123: 58751.97 | D123: Mohit | E123: =B123 -> 58751.97
A124: Suma | B124: 52008.03 | D124: Suma | E124: =B124 -> 52008.03
A125: Suraj | B125: 56404.215 | D125: Suraj | E125: =B125 -> 56404.215
A126: Grand Total | B126: 274364.01
A132: Day wise sum of sales
A135: Row Labels | B135: Sum of Sales
A136: 44357 | B136: 7674.15
A137: 44437 | B137: 4419.3
A138: 44454 | B138: 4526.58
A139: 44551 | B139: 4393.29
A140: 44657 | B140: 7812.09
A141: 44739 | B141: 7576.68
A142: 44804 | B142: 4756.2
A143: 44819 | B143: 5470.77
A144: 44863 | B144: 5014.71
A145: 45258 | B145: 4561.26
A146: 45327 | B146: 5968.38
A147: 45425 | B147: 4608.3
... A155: 45637 | B155: 5536.32
A156: Grand Total | B156: 118210.35
A170: Row Labels | B170: Sum of Profit | D170: City | E170: Sum of Profit
A171: Pune | B171: 5067.63 | D171: Pune | E171: =B171 -> 5067.63
A172: Nagpur | B172: 2427.81 | D172: Nagpur | E172: =B172 -> 2427.81
A173: Amravati | B173: 1160.37 | D173: Amravati | E173: =B173 -> 1160.37
A174: Mumbai | B174: -4917.885 | D174: Mumbai | E174: =B174 -> -4917.885
A175: Solapur | B175: 1289.52 | D175: Solapur | E175: =B175 -> 1289.52
A176: Agra | B176: 2568.24 | D176: Agra | E176: =B176 -> 2568.24
A177: Ajmer | B177: 1503.96 | D177: Ajmer | E177: =B177 -> 1503.96
A178: Akola | B178: 543.48 | D178: Akola | E178: =B178 -> 543.48
A179: Aligarh | B179: 492.84 | D179: Aligarh | E179: =B179 -> 492.84
A180: Allahabad | B180: 2130.36 | D180: Allahabad | E180: =B180 -> 2130.36
A181: Ambattur | B181: 35.1 | D181: Ambattur | E181: =B181 -> 35.1
A182: Amritsar | B182: 213.57 | D182: Amritsar | E182: =B182 -> 213.57
...

Sheet Sheet2
